tests/__init__.py
tests/test_webxplore.py
webxplore/WebScraper.py
webxplore/WebSearcher.py
webxplore/__init__.py
webxplore/searchBeyond/SearchNews.py
webxplore/searchBeyond/SearchReddit.py
webxplore/searchBeyond/SearchTwitter.py
webxplore/searchBeyond/__init__.py
webxplore/utils/SentimentAnalyzer.py
webxplore/utils/StripHTML.py
webxplore/utils/TextSummarizer.py
webxplore/utils/ToneAnalyzer.py
webxplore/utils/Utilities.py
webxplore/utils/__init__.py
WebXplore-1.0.3.dist-info/LICENSE
WebXplore-1.0.3.dist-info/METADATA
WebXplore-1.0.3.dist-info/WHEEL
WebXplore-1.0.3.dist-info/top_level.txt
WebXplore-1.0.3.dist-info/RECORD
