Metadata-Version: 2.1
Name: WebXplore
Version: 1.0.3
Summary: Explore Web Pages - Scrapers and Crawlers
Home-page: https://github.com/arnavn101/WebXplore
Author: Arnav Nidumolu
Author-email: arnav.nidumolu@gmail.com
License: UNKNOWN
Keywords: web crawling scraping nlp
Platform: UNKNOWN
Classifier: Programming Language :: Python :: 3
Classifier: License :: OSI Approved :: MIT License
Classifier: Topic :: Scientific/Engineering :: Artificial Intelligence
Classifier: Operating System :: OS Independent
Classifier: Intended Audience :: Developers
Classifier: Development Status :: 5 - Production/Stable
Requires-Python: >=3.7
Requires-Dist: nltk
Requires-Dist: requests
Requires-Dist: beautifulsoup4
Requires-Dist: google
Requires-Dist: numpy
Requires-Dist: pandas
Requires-Dist: textblob
Requires-Dist: sklearn
Requires-Dist: newsapi-python
Requires-Dist: praw
Requires-Dist: tweepy
Requires-Dist: readability-lxml
